ZeepLibrary/ZeepKeywords.py
ZeepLibrary/__init__.py
ZeepLibrary/version.py
robotframework_zeep-0.1.2.dist-info/DESCRIPTION.rst
robotframework_zeep-0.1.2.dist-info/METADATA
robotframework_zeep-0.1.2.dist-info/RECORD
robotframework_zeep-0.1.2.dist-info/WHEEL
robotframework_zeep-0.1.2.dist-info/metadata.json
robotframework_zeep-0.1.2.dist-info/top_level.txt
